nicefid/__init__.py
nicefid/check_download_inception.py
nicefid/cleanfid_resize.py
nicefid/compute_fid.py
nicefid/compute_kid.py
nicefid/features.py
nicefid/image_dataset.py
nicefid/inception_v3w.py
nicefid/list_images.py
nicefid/resize.py
nicefid/settings.py
nicefid/sqrtm_eig.py
nicefid-2.1.1.dist-info/LICENSE
nicefid-2.1.1.dist-info/WHEEL
nicefid-2.1.1.dist-info/METADATA
nicefid-2.1.1.dist-info/RECORD
