Metadata-Version: 2.1
Name: nicefid
Version: 2.1.1
Summary: Minimalistic FID and KID implementation. Reference checked against cleanfid
Home-page: https://github.com/samedii/nicefid
License: MIT
Author: Richard Löwenström
Author-email: samedii@gmail.com
Requires-Python: >=3.8,<4.0
Classifier: License :: OSI Approved :: MIT License
Classifier: Programming Language :: Python :: 3
Classifier: Programming Language :: Python :: 3.10
Classifier: Programming Language :: Python :: 3.8
Classifier: Programming Language :: Python :: 3.9
Requires-Dist: resize-right (>=0.0.2,<0.0.3)
Project-URL: Repository, https://github.com/samedii/nicefid
